dewi_logparsers/__init__.py
dewi_logparsers/loghandler.py
dewi_logparsers/syslog.py
dewi_logparsers/modules/__init__.py
dewi_logparsers/modules/ha.py
dewi_logparsers/modules/kernel.py
dewi_logparsers/modules/reboot.py
dewi_logparsers/modules/web.py
dewi_logparsers-2.1.0.dist-info/COPYING
dewi_logparsers-2.1.0.dist-info/METADATA
dewi_logparsers-2.1.0.dist-info/WHEEL
dewi_logparsers-2.1.0.dist-info/top_level.txt
dewi_logparsers-2.1.0.dist-info/zip-safe
dewi_logparsers-2.1.0.dist-info/RECORD
