Metadata-Version: 2.1
Name: dewi-logparsers
Version: 2.1.0
Summary: DEWI Logparser Module Framework: process / analyze syslog files
Home-page: https://github.com/LA-Toth/dewi_logparsers
Author: Laszlo Attila Toth
Author-email: python-dewi@laszloattilatoth.me
Maintainer: Laszlo Attila Toth
Maintainer-email: python-dewi@laszloattilatoth.me
License: LGPLv3
Keywords: tool framework development synchronization
Platform: UNKNOWN
Classifier: Development Status :: 5 - Production/Stable
Classifier: Environment :: Console
Classifier: Intended Audience :: Developers
Classifier: License :: OSI Approved :: GNU Lesser General Public License v3 (LGPLv3)
Classifier: Natural Language :: English
Classifier: Operating System :: POSIX
Classifier: Operating System :: POSIX :: Linux
Classifier: Operating System :: MacOS :: MacOS X
Classifier: Operating System :: Microsoft :: Windows
Classifier: Programming Language :: Python
Classifier: Programming Language :: Python :: 3 :: Only
Classifier: Programming Language :: Python :: 3.10
Classifier: Programming Language :: Python :: 3.11
Classifier: Topic :: Software Development
Classifier: Topic :: Software Development :: Libraries
Classifier: Topic :: Software Development :: Libraries :: Application Frameworks
Classifier: Topic :: Utilities
Requires-Python: >=3.10
License-File: COPYING
Requires-Dist: dewi-module-framework (>=2.0.1)
